[
null,
{"id":1,"expanded":true,"name":"MAP001","order":1,"parentId":0,"scrollX":816,"scrollY":824},
{"id":2,"expanded":true,"name":"MAP002","order":2,"parentId":0,"scrollX":811,"scrollY":466.5},
{"id":3,"expanded":false,"name":"MAP003","order":3,"parentId":2,"scrollX":819,"scrollY":474.5},
{"id":4,"expanded":false,"name":"MAP004","order":4,"parentId":0,"scrollX":11472,"scrollY":1166},
{"id":5,"expanded":false,"name":"MAP005","order":5,"parentId":0,"scrollX":815,"scrollY":470.5},
{"id":6,"expanded":false,"name":"MAP006","order":6,"parentId":0,"scrollX":815,"scrollY":470.5}
]